Workbook

Sheet products
A1: Product_ID | B1: Product_Name | C1: Category | D1: Unit_Price
A2: P101 | B2: Laptop | C2: Electronics | D2: 55000
A3: P102 | B3: Keyboard | C3: Accessories | D3: 2500
A4: P103 | B4: Mouse | C4: Accessories | D4: 800
A5: P104 | B5: Monitor | C5: Electronics | D5: 15000
A6: P105 | B6: Headphones | C6: Accessories | D6: 3500
A7: P106 | B7: Printer | C7: Electronics | D7: 12000
A8: P107 | B8: Tablet | C8: Electronics | D8: 22000
A9: P108 | B9: Webcam | C9: Accessories | D9: 3000
A10: P109 | B10: USB Drive | C10: Accessories | D10: 900
A11: P110 | B11: Smartphone | C11: Electronics | D11: 30000

Sheet customers
A1: Customer_ID | B1: Customer_Name | C1: City
A2: C001 | B2: Rahul Sharma | C2: Nagpur
A3: C002 | B3: Priya Patil | C3: Pune
A4: C003 | B4: Amit Verma | C4: Mumbai
A5: C004 | B5: Sneha Joshi | C5: Nashik
A6: C005 | B6: Rohit Singh | C6: Delhi
A7: C006 | B7: Neha Gupta | C7: Indore
A8: C007 | B8: Karan Mehta | C8: Bhopal
A9: C008 | B9: Pooja Deshmukh | C9: Aurangabad
A10: C009 | B10: Vikas Yadav | C10: Thane
A11: C010 | B11: Anjali Kulkarni | C11: Nagpur
A12: C011 | B12: Sahil Khan | C12: Pune
... A16: C015 | B16: Nitin More | C16: Nagpur

Sheet Sales
A1: Sale_ID | B1: Sale_Date | C1: Customer_ID | D1: Product_ID | E1: Quantity | F1: Unit_Price | G1: Salesperson | H1: Region | I1: Payment_Mode | J1: Total_Sales | K1: Product_Name | L1: Category | M1: Customer_Name | N1: City | O1: Sales_Category
A2: 1001 | B2: 46093 | C2: C001 | D2: P102 | E2: 4 | F2: 2500 | G2: Neha | H2: South | I2: UPI | J2: 10000 | K2: =_xlfn.XLOOKUP(Sales_Data[[#This Row],[Product_ID]],products!A:A,products!B:B,"Not Found") -> Keyboard | L2: =_xlfn.XLOOKUP(Sales_Data[[#This Row],[Product_ID]],products!A:A,products!C:C,"Not Found") -> Accessories | M2: =_xlfn.XLOOKUP(C2,customers!A:A,customers!B:B,"Not Found") -> Rahul Sharma | N2: =_xlfn.XLOOKUP(C1,customers!A:A,customers!C:C,"Not Found") -> City | O2: =IF(Sales_Data[[#This Row],[Total_Sales]]>=50000,"High","Low") -> Low
A3: 1002 | B3: 46174 | C3: C002 | D3: P109 | E3: 7 | F3: 900 | G3: Amit | H3: North | I3: UPI | J3: 6300 | K3: =_xlfn.XLOOKUP(Sales_Data[[#This Row],[Product_ID]],products!A:A,products!B:B,"Not Found") -> USB Drive | L3: =_xlfn.XLOOKUP(Sales_Data[[#This Row],[Product_ID]],products!A:A,products!C:C,"Not Found") -> Accessories | M3: =_xlfn.XLOOKUP(C3,customers!A:A,customers!B:B,"Not Found") -> Priya Patil | N3: =_xlfn.XLOOKUP(C2,customers!A:A,customers!C:C,"Not Found") -> Nagpur | O3: =IF(Sales_Data[[#This Row],[Total_Sales]]>=50000,"High","Low") -> Low
A4: 1003 | B4: 46152 | C4: C004 | D4: P104 | E4: 1 | F4: 15000 | G4: Sneha | H4: South | I4: Net Banking | J4: 15000 | K4: =_xlfn.XLOOKUP(Sales_Data[[#This Row],[Product_ID]],products!A:A,products!B:B,"Not Found") -> Monitor | L4: =_xlfn.XLOOKUP(Sales_Data[[#This Row],[Product_ID]],products!A:A,products!C:C,"Not Found") -> Electronics | M4: =_xlfn.XLOOKUP(C4,customers!A:A,customers!B:B,"Not Found") -> Sneha Joshi | N4: =_xlfn.XLOOKUP(C3,customers!A:A,customers!C:C,"Not Found") -> Pune | O4: =IF(Sales_Data[[#This Row],[Total_Sales]]>=50000,"High","Low") -> Low
A5: 1004 | B5: 46173 | C5: C008 | D5: P104 | E5: 5 | F5: 15000 | G5: Amit | H5: South | I5: Net Banking | J5: 75000 | K5: =_xlfn.XLOOKUP(Sales_Data[[#This Row],[Product_ID]],products!A:A,products!B:B,"Not Found") -> Monitor | L5: =_xlfn.XLOOKUP(Sales_Data[[#This Row],[Product_ID]],products!A:A,products!C:C,"Not Found") -> Electronics | M5: =_xlfn.XLOOKUP(C5,customers!A:A,customers!B:B,"Not Found") -> Pooja Deshmukh | N5: =_xlfn.XLOOKUP(C4,customers!A:A,customers!C:C,"Not Found") -> Nashik | O5: =IF(Sales_Data[[#This Row],[Total_Sales]]>=50000,"High","Low") -> High
A6: 1005 | B6: 46062 | C6: C005 | D6: P106 | E6: 4 | F6: 12000 | G6: Rahul | H6: North | I6: UPI | J6: 48000 | K6: =_xlfn.XLOOKUP(Sales_Data[[#This Row],[Product_ID]],products!A:A,products!B:B,"Not Found") -> Printer | L6: =_xlfn.XLOOKUP(Sales_Data[[#This Row],[Product_ID]],products!A:A,products!C:C,"Not Found") -> Electronics | M6: =_xlfn.XLOOKUP(C6,customers!A:A,customers!B:B,"Not Found") -> Rohit Singh | N6: =_xlfn.XLOOKUP(C5,customers!A:A,customers!C:C,"Not Found") -> Aurangabad | O6: =IF(Sales_Data[[#This Row],[Total_Sales]]>=50000,"High","Low") -> Low
A7: 1006 | B7: 46114 | C7: C002 | D7: P107 | E7: 6 | F7: 22000 | G7: Sneha | H7: East | I7: UPI | J7: 132000 | K7: =_xlfn.XLOOKUP(Sales_Data[[#This Row],[Product_ID]],products!A:A,products!B:B,"Not Found") -> Tablet | L7: =_xlfn.XLOOKUP(Sales_Data[[#This Row],[Product_ID]],products!A:A,products!C:C,"Not Found") -> Electronics | M7: =_xlfn.XLOOKUP(C7,customers!A:A,customers!B:B,"Not Found") -> Priya Patil | N7: =_xlfn.XLOOKUP(C6,customers!A:A,customers!C:C,"Not Found") -> Delhi | O7: =IF(Sales_Data[[#This Row],[Total_Sales]]>=50000,"High","Low") -> High
A8: 1007 | B8: 46054 | C8: C009 | D8: P108 | E8: 7 | F8: 3000 | G8: Amit | H8: Central | I8: Card | J8: 21000 | K8: =_xlfn.XLOOKUP(Sales_Data[[#This Row],[Product_ID]],products!A:A,products!B:B,"Not Found") -> Webcam | L8: =_xlfn.XLOOKUP(Sales_Data[[#This Row],[Product_ID]],products!A:A,products!C:C,"Not Found") -> Accessories | M8: =_xlfn.XLOOKUP(C8,customers!A:A,customers!B:B,"Not Found") -> Vikas Yadav | N8: =_xlfn.XLOOKUP(C7,customers!A:A,customers!C:C,"Not Found") -> Pune | O8: =IF(Sales_Data[[#This Row],[Total_Sales]]>=50000,"High","Low") -> Low
A9: 1008 | B9: 46115 | C9: C015 | D9: P110 | E9: 4 | F9: 30000 | G9: Vikas | H9: North | I9: UPI | J9: 120000 | K9: =_xlfn.XLOOKUP(Sales_Data[[#This Row],[Product_ID]],products!A:A,products!B:B,"Not Found") -> Smartphone | L9: =_xlfn.XLOOKUP(Sales_Data[[#This Row],[Product_ID]],products!A:A,products!C:C,"Not Found") -> Electronics | M9: =_xlfn.XLOOKUP(C9,customers!A:A,customers!B:B,"Not Found") -> Nitin More | N9: =_xlfn.XLOOKUP(C8,customers!A:A,customers!C:C,"Not Found") -> Thane | O9: =IF(Sales_Data[[#This Row],[Total_Sales]]>=50000,"High","Low") -> High
A10: 1009 | B10: 46097 | C10: C013 | D10: P104 | E10: 2 | F10: 15000 | G10: Neha | H10: North | I10: Net Banking | J10: 30000 | K10: =_xlfn.XLOOKUP(Sales_Data[[#This Row],[Product_ID]],products!A:A,products!B:B,"Not Found") -> Monitor | L10: =_xlfn.XLOOKUP(Sales_Data[[#This Row],[Product_ID]],products!A:A,products!C:C,"Not Found") -> Electronics | M10: =_xlfn.XLOOKUP(C10,customers!A:A,customers!B:B,"Not Found") -> Akash Jain | N10: =_xlfn.XLOOKUP(C9,customers!A:A,customers!C:C,"Not Found") -> Nagpur | O10: =IF(Sales_Data[[#This Row],[Total_Sales]]>=50000,"High","Low") -> Low
A11: 1010 | B11: 46185 | C11: C008 | D11: P105 | E11: 6 | F11: 3500 | G11: Neha | H11: East | I11: Card | J11: 21000 | K11: =_xlfn.XLOOKUP(Sales_Data[[#This Row],[Product_ID]],products!A:A,products!B:B,"Not Found") -> Headphones | L11: =_xlfn.XLOOKUP(Sales_Data[[#This Row],[Product_ID]],products!A:A,products!C:C,"Not Found") -> Accessories | M11: =_xlfn.XLOOKUP(C11,customers!A:A,customers!B:B,"Not Found") -> Pooja Deshmukh | N11: =_xlfn.XLOOKUP(C10,customers!A:A,customers!C:C,"Not Found") -> Nashik | O11: =IF(Sales_Data[[#This Row],[Total_Sales]]>=50000,"High","Low") -> Low
A12: 1011 | B12: 46091 | C12: C011 | D12: P104 | E12: 2 | F12: 15000 | G12: Sneha | H12: South | I12: Cash | J12: 30000 | K12: =_xlfn.XLOOKUP(Sales_Data[[#This Row],[Product_ID]],products!A:A,products!B:B,"Not Found") -> Monitor | L12: =_xlfn.XLOOKUP(Sales_Data[[#This Row],[Product_ID]],products!A:A,products!C:C,"Not Found") -> Electronics | M12: =_xlfn.XLOOKUP(C12,customers!A:A,customers!B:B,"Not Found") -> Sahil Khan | N12: =_xlfn.XLOOKUP(C11,customers!A:A,customers!C:C,"Not Found") -> Aurangabad | O12: =IF(Sales_Data[[#This Row],[Total_Sales]]>=50000,"High","Low") -> Low
A13: 1012 | B13: 46120 | C13: C008 | D13: P103 | E13: 5 | F13: 800 | G13: Vikas | H13: Central | I13: Cash | J13: 4000 | K13: =_xlfn.XLOOKUP(Sales_Data[[#This Row],[Product_ID]],products!A:A,products!B:B,"Not Found") -> Mouse | L13: =_xlfn.XLOOKUP(Sales_Data[[#This Row],[Product_ID]],products!A:A,products!C:C,"Not Found") -> Accessories | M13: =_xlfn.XLOOKUP(C13,customers!A:A,customers!B:B,"Not Found") -> Pooja Deshmukh | N13: =_xlfn.XLOOKUP(C12,customers!A:A,customers!C:C,"Not Found") -> Pune | O13: =IF(Sales_Data[[#This Row],[Total_Sales]]>=50000,"High","Low") -> Low
... A501: 1500 | B501: 46174 | C501: C006 | D501: P108 | E501: 8 | F501: 3000 | G501: Neha | H501: Central | I501: Cash | J501: 24000 | K501: =_xlfn.XLOOKUP(Sales_Data[[#This Row],[Product_ID]],products!A:A,products!B:B,"Not Found") -> Webcam | L501: =_xlfn.XLOOKUP(Sales_Data[[#This Row],[Product_ID]],products!A:A,products!C:C,"Not Found") -> Accessories | M501: =_xlfn.XLOOKUP(C501,customers!A:A,customers!B:B,"Not Found") -> Neha Gupta | N501: =_xlfn.XLOOKUP(C500,customers!A:A,customers!C:C,"Not Found") -> Indore | O501: =IF(Sales_Data[[#This Row],[Total_Sales]]>=50000,"High","Low") -> Low

Sheet Sales_Report
G1: SALES DATA ANALYSIS REPORT
B4: Total Sales | E4: Total Orders | I4: Total Quantity | N4: Average Sale
B5: =SUM(Sales!J:J) -> 30649600 | E5: =COUNTA(Sales!A:A)-1 -> 500 | I5: =SUM(Sales!E:E) -> 2259 | N5: =AVERAGE(Sales!J:J) -> 61299.2
C8: CITY-WISE SALES | G8: SALES PERSON-WISE SALES | M8: CATEGORY-WISE SALES
C10: City | D10: Total Sales | G10: Sales Person | H10: Total_Sales | M10: Category | N10: Total_Sales
C11: Aurangabad | D11: 1113700 | G11: Amit | H11: 5801900 | M11: Accessories | N11: 2654600
C12: Bhopal | D12: 1756200 | G12: Neha | H12: 5375400 | M12: Electronics | N12: 27995000
C13: Delhi | D13: 2038000 | G13: Priya | H13: 4760400 | M13: Grand Total | N13: 30649600
C14: Indore | D14: 6132400 | G14: Rahul | H14: 5420600
C15: Mumbai | D15: 4738400 | G15: Sneha | H15: 5164500
C16: Nagpur | D16: 5038900 | G16: Vikas | H16: 4126800
C17: Nashik | D17: 3276600 | G17: Grand Total | H17: 30649600
C18: Pune | D18: 3876700
C19: Thane | D19: 2678700
C20: Grand Total | D20: 30649600
